chart_scraper/ChartScraper.py
chart_scraper/__init__.py
scrape_charts-1.2.0.dist-info/LICENSE
scrape_charts-1.2.0.dist-info/METADATA
scrape_charts-1.2.0.dist-info/WHEEL
scrape_charts-1.2.0.dist-info/top_level.txt
scrape_charts-1.2.0.dist-info/RECORD
