Metadata-Version: 2.1
Name: scrape-charts
Version: 1.2.0
Summary: Scrape a websites chart into either a list, dict, or pandas dataframe
Home-page: https://github.com/Pshah2023/scrape_charts
Author: Pranit_P_Shah
Author-email: pranitpshah@gmail.com
License: UNKNOWN
Project-URL: Bug Tracker, https://github.com/Pshah2023/scrape_charts/issues
Platform: UNKNOWN
Classifier: Programming Language :: Python :: 3
Classifier: Operating System :: OS Independent
Classifier: Natural Language :: English
Requires-Python: >=3.6
License-File: LICENSE
